<?xml version="1.0" encoding="iso-8859-15"?>
<sigfile>
  <function>
    <id>E5B3CE1A58906991</id>
    <version>
      <size>0x000000000000005C</size>
      <parent_id>6AC3B5E1C82E804B</parent_id>
      <address>455290</address>
      <flags>0x4400</flags>
      <signatures>
        <signature algo="crc32" method="invariants">2AB4CC03</signature>
      </signatures>
      <xrefs>
        <xref offset="0x00000000FFFFFFFF">0A01ACCD3CA2916F</xref>
        <xref offset="0x0000000000000000" size="0x000000000000000D">905553BA21644851</xref>
        <xref offset="0x000000000000000D" size="0x0000000000000005">C47D8CB5B30368BA</xref>
        <xref offset="0x0000000000000012" size="0x0000000000000019">81E76CFB04B299E6</xref>
        <xref offset="0x000000000000002B" size="0x0000000000000009">504B33FD2E05DE4A</xref>
        <xref offset="0x0000000000000034" size="0x000000000000000A">4DDCAEBB2C83B84D</xref>
        <xref offset="0x000000000000003E" size="0x000000000000000A">77A021EBEC923338</xref>
        <xref offset="0x0000000000000048" size="0x0000000000000009">529C12529B5EADC3</xref>
        <xref offset="0x0000000000000051" size="0x0000000000000009">41AFE913C8772099</xref>
        <xref offset="0x000000000000005A" size="0x0000000000000002">AABC9FEF783AC6D9</xref>
      </xrefs>
    </version>
  </function>
</sigfile>
