<?xml version="1.0" encoding="iso-8859-15"?>
<sigfile>
  <basic_block>
    <id>AEDB331215DEAD5E</id>
    <version>
      <size>0x0000000000000013</size>
      <parent_id>86D602FB71C93A70</parent_id>
      <address>4D111F</address>
      <signatures>
        <signature algo="crc32" method="invariants">A84D7CBD</signature>
      </signatures>
      <offsets>
        <valueview offset="0000000000000000" operand="00000001">stack</valueview>
        <valueview offset="0000000000000004" operand="00000000">offset-off32</valueview>
        <valueview offset="000000000000000C" operand="00000000">offset-off32</valueview>
      </offsets>
      <xrefs>
        <xref offset="0x0000000000000004">B217306506662A70</xref>
        <xref offset="0x000000000000000C">7F580E772EBF4189</xref>
        <xref offset="0x0000000000000013">734DABBC8D90977A</xref>
        <xref offset="0x000000000000001D">AFE19C7916E03EAF</xref>
      </xrefs>
    </version>
  </basic_block>
</sigfile>
