<?xml version="1.0" encoding="iso-8859-15"?>
<sigfile>
  <basic_block>
    <id>ED901C1935635546</id>
    <version>
      <size>0x0000000000000012</size>
      <parent_id>F1ADCD6F4EB92660</parent_id>
      <address>4D0B68</address>
      <signatures>
        <signature algo="crc32" method="invariants">948854D0</signature>
      </signatures>
      <xrefs>
        <xref offset="0x0000000000000012">97AC993AB848E293</xref>
        <xref offset="0x0000000000000109">66BEAE3C55113D06</xref>
      </xrefs>
    </version>
  </basic_block>
</sigfile>
