<?xml version="1.0" encoding="iso-8859-15"?>
<sigfile>
  <stackframe_member>
    <id>53C7C361077EA25E</id>
    <version>
      <size>0x0000000000000008</size>
      <parent_id>DB06880136110F81</parent_id>
      <address>30</address>
      <userdefinedname>var_210</userdefinedname>
      <proto>DDCOLORKEY</proto>
      <flags>0x60000400</flags>
      <signatures/>
      <xrefs>
        <xref offset="0x0000000000000000">4F5FEF0551B9EFB7</xref>
      </xrefs>
    </version>
  </stackframe_member>
</sigfile>
