<?xml version="1.0" encoding="iso-8859-15"?>
<sigfile>
  <stackframe>
    <id>0D24F116F1DA4789</id>
    <version>
      <size>0x000000000000001E</size>
      <parent_id>99B9EF718CEB34AA</parent_id>
      <address>4D9700</address>
      <userdefinedname>$ F4D9700</userdefinedname>
      <signatures/>
      <xrefs>
        <xref offset="0x0000000000000010">8AA94ADF96642D22</xref>
        <xref offset="0x0000000000000018">45CA21494113D1E5</xref>
        <xref offset="0x000000000000001C">FA3FBFA4BB98608F</xref>
      </xrefs>
      <attribute key="stack_lvars">0x0000000C</attribute>
      <attribute key="stack_regvars">0x00000000</attribute>
      <attribute key="stack_args">0x00000000</attribute>
    </version>
  </stackframe>
</sigfile>
