<?xml version="1.0" encoding="iso-8859-15"?>
<sigfile>
  <stackframe>
    <id>0E2AF898F78415F1</id>
    <version>
      <size>0x0000000000000004</size>
      <parent_id>B36AA3738EADA3D8</parent_id>
      <address>418A90</address>
      <userdefinedname>$ F418A90</userdefinedname>
      <signatures/>
      <xrefs/>
      <attribute key="stack_lvars">0x00000000</attribute>
      <attribute key="stack_regvars">0x00000000</attribute>
      <attribute key="stack_args">0x00000000</attribute>
    </version>
  </stackframe>
</sigfile>
