<?xml version="1.0" encoding="iso-8859-15"?>
<sigfile>
  <stackframe>
    <id>BC5A01EA4F2059A8</id>
    <version>
      <size>0x0000000000000008</size>
      <parent_id>583601A66DABB646</parent_id>
      <address>4A9890</address>
      <userdefinedname>$ F4A9890</userdefinedname>
      <signatures/>
      <xrefs/>
      <attribute key="stack_lvars">0x00000004</attribute>
      <attribute key="stack_regvars">0x00000000</attribute>
      <attribute key="stack_args">0x00000000</attribute>
    </version>
  </stackframe>
</sigfile>
